__init__.py
eatshell.py
eatshell-1.0.2.dist-info/LICENSE
eatshell-1.0.2.dist-info/METADATA
eatshell-1.0.2.dist-info/WHEEL
eatshell-1.0.2.dist-info/entry_points.txt
eatshell-1.0.2.dist-info/top_level.txt
eatshell-1.0.2.dist-info/RECORD
