Metadata-Version: 2.1
Name: eatshell
Version: 1.0.2
Summary: Automate the process of extracting, loading and assembling shellcode.
Author-email: sapphicart <shrutipriya44@gmail.com>
License: MIT License
Project-URL: Homepage, https://github.com/sapphicart/eatshell
Project-URL: Issues, https://github.com/sapphicart/eatshell/issues
Keywords: python,shellcode-extractor,shellcode-loader,shellcode-assembler,shellcode
Classifier: Programming Language :: Python :: 3
Classifier: Operating System :: OS Independent
Requires-Python: >=3.8
License-File: LICENSE
Requires-Dist: click
Requires-Dist: colorama
Requires-Dist: pwntools
Requires-Dist: python-dotenv
